odoo8_addon_privacy_right_to_be_forgotten-8.0.1.0.0.99.dev2-py2.7-nspkg.pth
odoo8_addon_privacy_right_to_be_forgotten-8.0.1.0.0.99.dev2.dist-info/METADATA
odoo8_addon_privacy_right_to_be_forgotten-8.0.1.0.0.99.dev2.dist-info/RECORD
odoo8_addon_privacy_right_to_be_forgotten-8.0.1.0.0.99.dev2.dist-info/WHEEL
odoo8_addon_privacy_right_to_be_forgotten-8.0.1.0.0.99.dev2.dist-info/namespace_packages.txt
odoo8_addon_privacy_right_to_be_forgotten-8.0.1.0.0.99.dev2.dist-info/top_level.txt
odoo_addons/privacy_right_to_be_forgotten/README.rst
odoo_addons/privacy_right_to_be_forgotten/__init__.py
odoo_addons/privacy_right_to_be_forgotten/__openerp__.py
odoo_addons/privacy_right_to_be_forgotten/data/ir_actions_act_window.xml
odoo_addons/privacy_right_to_be_forgotten/i18n/fr.po
odoo_addons/privacy_right_to_be_forgotten/i18n/privacy_right_to_be_forgotten.pot
odoo_addons/privacy_right_to_be_forgotten/models/__init__.py
odoo_addons/privacy_right_to_be_forgotten/static/description/icon.png
odoo_addons/privacy_right_to_be_forgotten/tests/__init__.py
odoo_addons/privacy_right_to_be_forgotten/tests/test_privacy_right_to_be_forgotten.py
odoo_addons/privacy_right_to_be_forgotten/views/res_partner_gdpr.xml
odoo_addons/privacy_right_to_be_forgotten/wizards/__init__.py
odoo_addons/privacy_right_to_be_forgotten/wizards/res_partner_gdpr.py
